{"max_resources":[740500,1481000,2336,1518],"name":"Kernel System","children":[{"name":"Static Partition","type":"partition","children":[{"name":"Board interface","type":"resource","data":[113900,227800,377,0],"details":[{"text":"Platform interface logic.","type":"text"}]}]},{"name":"Global interconnect","type":"resource","data":[1945,3726,61,0],"details":[{"text":"Global interconnect for 2 global loads and 2 global stores. Reduce number of global loads and stores to simplify global interconnect.","type":"text"},{"text":"See %L for more information","type":"text","links":[{"link":"https://www.altera.com/documentation/mwh1391807516407.html#hnj1476724450050","guide":"Best Practices Guide : Global Memory Interconnect"}]}]},{"name":"System description ROM","type":"resource","data":[0,67,2,0],"details":[{"text":"This read-only memory contains information for the host about the system and about each kernel in the system, including kernel names, arguments, and attributes.  The system description ROM ensures that the binary image on the FPGA is compatible with the host program.","type":"text"}]},{"name":"fnnls_channels_pass_thru_channels.cl:28 (ch_control_data_d2w)","debug":[[{"filename":"/data/vkhriste/test-regression/multifit_ocl/device/fnnls_channels_pass_thru_channels.cl","line":28}]],"type":"resource","data":[30,208,0,0],"details":[{"text":"Channel array with 2 elements. Each channel is implemented 32 bits wide by 1 deep.","type":"text"},{"text":"Requested depth was 0.","type":"text"},{"text":"Channel depth was changed for the following reason:","type":"text","details":[{"text":"instruction scheduling requirements","type":"text"}]},{"text":"See %L for more information","type":"text","links":[{"link":"https://www.altera.com/documentation/mwh1391807516407.html#qah1476410829821","guide":"Best Practices Guide : Channels"}]}]},{"name":"fnnls_channels_pass_thru_channels.cl:29 (ch_control_data_w2c)","debug":[[{"filename":"/data/vkhriste/test-regression/multifit_ocl/device/fnnls_channels_pass_thru_channels.cl","line":29}]],"type":"resource","data":[22,140,0,0],"details":[{"text":"Channel array with 2 elements. Each channel is implemented 32 bits wide by 1 deep.","type":"text"},{"text":"Requested depth was 0.","type":"text"},{"text":"Channel depth was changed for the following reason:","type":"text","details":[{"text":"instruction scheduling requirements","type":"text"}]},{"text":"See %L for more information","type":"text","links":[{"link":"https://www.altera.com/documentation/mwh1391807516407.html#qah1476410829821","guide":"Best Practices Guide : Channels"}]}]},{"name":"fnnls_channels_pass_thru_channels.cl:30 (ch_data_d2w)","debug":[[{"filename":"/data/vkhriste/test-regression/multifit_ocl/device/fnnls_channels_pass_thru_channels.cl","line":30}]],"type":"resource","data":[30,12496,0,0],"details":[{"text":"Channel array with 2 elements. Each channel is implemented 2080 bits wide by 1 deep.","type":"text"},{"text":"Requested depth was 0.","type":"text"},{"text":"Channel depth was changed for the following reason:","type":"text","details":[{"text":"instruction scheduling requirements","type":"text"}]},{"text":"See %L for more information","type":"text","links":[{"link":"https://www.altera.com/documentation/mwh1391807516407.html#qah1476410829821","guide":"Best Practices Guide : Channels"}]}]},{"name":"fnnls_channels_pass_thru_channels.cl:31 (ch_data_w2c)","debug":[[{"filename":"/data/vkhriste/test-regression/multifit_ocl/device/fnnls_channels_pass_thru_channels.cl","line":31}]],"type":"resource","data":[22,1292,0,0],"details":[{"text":"Channel array with 2 elements. Each channel is implemented 320 bits wide by 1 deep.","type":"text"},{"text":"Requested depth was 0.","type":"text"},{"text":"Channel depth was changed for the following reason:","type":"text","details":[{"text":"instruction scheduling requirements","type":"text"}]},{"text":"See %L for more information","type":"text","links":[{"link":"https://www.altera.com/documentation/mwh1391807516407.html#qah1476410829821","guide":"Best Practices Guide : Channels"}]}]},{"name":"collector","total_kernel_resources":[8074,13620,37,0],"debug":[[{"filename":"/data/vkhriste/test-regression/multifit_ocl/device/fnnls_channels_pass_thru_channels.cl","line":134}]],"type":"function","total_percent":[1.92968,1.09034,0.919649,1.5839,0],"children":[{"detail":[{"text":"Feedback + Cluster logic","type":"text"}],"name":"Data control overhead","type":"resource","data":[1650,711,2,0]},{"name":"Private Variable: \n - 'num_channels_completed' (fnnls_channels_pass_thru_channels.cl:134)","type":"resource","data":[0,56,1,0],"details":[{"text":"Type: Register","type":"text"},{"text":"1 register of width 32 and depth 85","type":"text"}]},{"name":"No Source Line","children":[{"count":1,"name":"State","debug":[[{"filename":"","line":0}]],"type":"resource","data":[731,1457,0,0]},{"count":2,"debug":[[{"filename":"","line":0}]],"name":"And","data":[42,0,0,0],"type":"resource"}],"type":"resource","data":[773,1457,0,0]},{"replace_name":"true","debug":[[{"filename":"/data/vkhriste/test-regression/multifit_ocl/device/fnnls_channels_pass_thru_channels.cl","line":134}]],"name":"/data/vkhriste/test-regression/multifit_ocl/device/fnnls_channels_pass_thru_channels.cl:134","children":[{"count":2,"name":"32-bit Integer Add","debug":[[{"filename":"/data/vkhriste/test-regression/multifit_ocl/device/fnnls_channels_pass_thru_channels.cl","line":134}]],"type":"resource","data":[22,0,0,0]}],"data":[22,0,0,0],"type":"resource"},{"replace_name":"true","debug":[[{"filename":"/data/vkhriste/test-regression/multifit_ocl/device/fnnls_channels_pass_thru_channels.cl","line":137}]],"name":"/data/vkhriste/test-regression/multifit_ocl/device/fnnls_channels_pass_thru_channels.cl:137","children":[{"count":4,"name":"32-bit Integer Add","debug":[[{"filename":"/data/vkhriste/test-regression/multifit_ocl/device/fnnls_channels_pass_thru_channels.cl","line":137}]],"type":"resource","data":[55,0,0,0]},{"count":1,"name":"And","debug":[[{"filename":"/data/vkhriste/test-regression/multifit_ocl/device/fnnls_channels_pass_thru_channels.cl","line":137}]],"type":"resource","data":[1,1,0,0]},{"count":2,"name":"Non-Blocking Channel Read","debug":[[{"filename":"/data/vkhriste/test-regression/multifit_ocl/device/fnnls_channels_pass_thru_channels.cl","line":137}]],"type":"resource","data":[2,0,0,0]},{"count":1,"name":"Store","debug":[[{"filename":"/data/vkhriste/test-regression/multifit_ocl/device/fnnls_channels_pass_thru_channels.cl","line":137}]],"type":"resource","data":[2747,5696,17,0]}],"data":[2805,5697,17,0],"type":"resource"},{"replace_name":"true","debug":[[{"filename":"/data/vkhriste/test-regression/multifit_ocl/device/fnnls_channels_pass_thru_channels.cl","line":138}]],"name":"/data/vkhriste/test-regression/multifit_ocl/device/fnnls_channels_pass_thru_channels.cl:138","children":[{"count":4,"name":"32-bit Integer Add","debug":[[{"filename":"/data/vkhriste/test-regression/multifit_ocl/device/fnnls_channels_pass_thru_channels.cl","line":138}]],"type":"resource","data":[55,0,0,0]},{"count":1,"name":"And","debug":[[{"filename":"/data/vkhriste/test-regression/multifit_ocl/device/fnnls_channels_pass_thru_channels.cl","line":138}]],"type":"resource","data":[1,1,0,0]},{"count":2,"name":"Non-Blocking Channel Read","debug":[[{"filename":"/data/vkhriste/test-regression/multifit_ocl/device/fnnls_channels_pass_thru_channels.cl","line":138}]],"type":"resource","data":[2,0,0,0]},{"count":1,"name":"Store","debug":[[{"filename":"/data/vkhriste/test-regression/multifit_ocl/device/fnnls_channels_pass_thru_channels.cl","line":138}]],"type":"resource","data":[2747,5696,17,0]}],"data":[2805,5697,17,0],"type":"resource"},{"replace_name":"true","debug":[[{"filename":"/data/vkhriste/test-regression/multifit_ocl/device/fnnls_channels_pass_thru_channels.cl","line":140}]],"name":"/data/vkhriste/test-regression/multifit_ocl/device/fnnls_channels_pass_thru_channels.cl:140","children":[{"count":3,"name":"And","debug":[[{"filename":"/data/vkhriste/test-regression/multifit_ocl/device/fnnls_channels_pass_thru_channels.cl","line":140}]],"type":"resource","data":[2,0,0,0]},{"count":3,"name":"Integer Compare","debug":[[{"filename":"/data/vkhriste/test-regression/multifit_ocl/device/fnnls_channels_pass_thru_channels.cl","line":140}]],"type":"resource","data":[15,0,0,0]},{"count":1,"name":"Iteration Initiation","debug":[[{"filename":"/data/vkhriste/test-regression/multifit_ocl/device/fnnls_channels_pass_thru_channels.cl","line":140}]],"type":"resource","data":[2,2,0,0]}],"data":[19,2,0,0],"type":"resource"}],"data":[8074,13620,37,0],"details":[{"text":"Number of compute units: 1","type":"text"},{"text":"Max global work dimension: 0","type":"text"}],"compute_units":1},{"name":"dispatcher_matrix_units","total_kernel_resources":[26131,29280,162,2],"debug":[[{"filename":"/data/vkhriste/test-regression/multifit_ocl/device/fnnls_channels_pass_thru_channels.cl","line":38}]],"type":"function","total_percent":[5.14602,3.52883,1.97704,6.93493,0.131752],"children":[{"detail":[{"text":"Feedback + Cluster logic","type":"text"}],"name":"Data control overhead","type":"resource","data":[11159,8255,0,0]},{"name":"Coalesced Private Variables: \n - 'ich' (fnnls_channels_pass_thru_channels.cl:38)\n - 'ctl_data' (fnnls_channels_pass_thru_channels.cl:74)","type":"resource","data":[7,36,0,0],"details":[{"text":"Type: Register","type":"text"},{"text":"1 register of width 32 and depth 1","type":"text"}]},{"name":"Private Variable: \n - 'data' (fnnls_channels_pass_thru_channels.cl:51)","type":"resource","data":[70,360,0,0],"details":[{"text":"Type: Register","type":"text"},{"text":"10 registers of width 32 and depth 1","type":"text"}]},{"name":"Private Variable: \n - 'i' (fnnls_channels_pass_thru_channels.cl:44)","type":"resource","data":[7,36,0,0],"details":[{"text":"Type: Register","type":"text"},{"text":"1 register of width 32 and depth 1","type":"text"}]},{"name":"Private Variable: \n - 'i' (fnnls_channels_pass_thru_channels.cl:64)","type":"resource","data":[7,36,0,0],"details":[{"text":"Type: Register","type":"text"},{"text":"1 register of width 32 and depth 1","type":"text"}]},{"name":"Private Variable: \n - 'j' (fnnls_channels_pass_thru_channels.cl:48)","type":"resource","data":[7,36,0,0],"details":[{"text":"Type: Register","type":"text"},{"text":"1 register of width 32 and depth 1","type":"text"}]},{"name":"Private Variable: \n - 'j' (fnnls_channels_pass_thru_channels.cl:55)","type":"resource","data":[7,36,0,0],"details":[{"text":"Type: Register","type":"text"},{"text":"1 register of width 32 and depth 1","type":"text"}]},{"name":"Private Variable: \n - 'k' (fnnls_channels_pass_thru_channels.cl:58)","type":"resource","data":[7,36,0,0],"details":[{"text":"Type: Register","type":"text"},{"text":"1 register of width 32 and depth 1","type":"text"}]},{"name":"Private Variable: \n - 'k' (fnnls_channels_pass_thru_channels.cl:67)","type":"resource","data":[7,36,0,0],"details":[{"text":"Type: Register","type":"text"},{"text":"1 register of width 32 and depth 1","type":"text"}]},{"name":"Private Variable: \n - 'v' (fnnls_channels_pass_thru_channels.cl:41)","type":"resource","data":[70,360,0,0],"details":[{"text":"Type: Register","type":"text"},{"text":"10 registers of width 32 and depth 1","type":"text"}]},{"name":"fnnls_channels_pass_thru_channels.cl:40 (m)","type":"resource","data":[33,256,2,0],"details":[{"Private memory":"Good but replicated","Total replication":8,"Number of banks":1,"Bank depth":"128 words","Additional information":[{"text":"Requested size 400 bytes, implemented size 4096 bytes, replicated 8 times total, stall-free, 3 reads and 1 write. ","type":"text"},{"text":"Replicated 8 times to create private copies for simultaneous execution of 8 threads in the loop containing accesses to the array.","type":"text"}],"Implemented size":"4096 bytes","Bank width":"32 bits","Reference":[{"text":"See %L for more information.","type":"text","links":[{"link":"https://www.altera.com/documentation/mwh1391807516407.html#chn1469549457114","guide":"Best Practices Guide : Local Memory"}]}],"Requested size":"400 bytes","Clock":"Running memory at 2x clock to support more concurrent ports","type":"table"},{"text":"Private memory implemented in on-chip block RAM.","type":"text"}]},{"name":"fnnls_channels_pass_thru_channels.cl:51 (data)","type":"resource","data":[33,4864,74,0],"details":[{"Private memory":"Good but replicated","Total replication":296,"Number of banks":1,"Bank depth":"64 words","Additional information":[{"text":"Requested size 220 bytes, implemented size 75776 bytes, replicated 296 times total, stall-free, 110 reads and 1 write. ","type":"text"},{"text":"Replicated 8 times to create private copies for simultaneous execution of 8 threads in the loop containing accesses to the array.","type":"text"},{"text":"Replicated 37 times to efficiently support multiple accesses. To reduce this replication factor, reduce number of read and write accesses.","type":"text"}],"Implemented size":"75776 bytes","Bank width":"32 bits","Reference":[{"text":"See %L for more information.","type":"text","links":[{"link":"https://www.altera.com/documentation/mwh1391807516407.html#chn1469549457114","guide":"Best Practices Guide : Local Memory"}]}],"Requested size":"220 bytes","Clock":"Running memory at 2x clock to support more concurrent ports","type":"table"},{"text":"Private memory implemented in on-chip block RAM.","type":"text"}]},{"name":"No Source Line","children":[{"count":6,"name":"State","data":[2584,1614,0,0],"debug":[[{"filename":"","line":0}]],"type":"resource"},{"count":1,"name":"And","data":[11,0,0,0],"debug":[[{"filename":"","line":0}]],"type":"resource"},{"count":3,"name":"Case Statement","data":[256,32,0,0],"debug":[[{"filename":"","line":0}]],"type":"resource"},{"count":2,"name":"Hardened Floating-point Accumulator","data":[0,0,0,2],"debug":[[{"filename":"","line":0}]],"type":"resource"},{"count":21,"name":"Integer Compare","data":[231,0,0,0],"debug":[[{"filename":"","line":0}]],"type":"resource"},{"count":20,"name":"Select","data":[520,0,0,0],"debug":[[{"filename":"","line":0}]],"type":"resource"}],"type":"resource","data":[3602,1646,0,2]},{"replace_name":"true","debug":[[{"filename":"/data/vkhriste/test-regression/multifit_ocl/device/fnnls_channels_pass_thru_channels.cl","line":38}]],"name":"/data/vkhriste/test-regression/multifit_ocl/device/fnnls_channels_pass_thru_channels.cl:38","children":[{"count":7,"name":"32-bit Integer Add","data":[99,0,0,0],"debug":[[{"filename":"/data/vkhriste/test-regression/multifit_ocl/device/fnnls_channels_pass_thru_channels.cl","line":38}]],"type":"resource"},{"count":4,"name":"Integer Compare","data":[33,0,0,0],"debug":[[{"filename":"/data/vkhriste/test-regression/multifit_ocl/device/fnnls_channels_pass_thru_channels.cl","line":38}]],"type":"resource"}],"data":[132,0,0,0],"type":"resource"},{"replace_name":"true","debug":[[{"filename":"/data/vkhriste/test-regression/multifit_ocl/device/fnnls_channels_pass_thru_channels.cl","line":42}]],"name":"/data/vkhriste/test-regression/multifit_ocl/device/fnnls_channels_pass_thru_channels.cl:42","children":[{"count":2,"name":"32-bit Integer Add","data":[22,0,0,0],"debug":[[{"filename":"/data/vkhriste/test-regression/multifit_ocl/device/fnnls_channels_pass_thru_channels.cl","line":42}]],"type":"resource"}],"data":[22,0,0,0],"type":"resource"},{"name":"/data/vkhriste/test-regression/multifit_ocl/device/fnnls_channels_pass_thru_channels.cl:64","debug":[[{"filename":"/data/vkhriste/test-regression/multifit_ocl/device/fnnls_channels_pass_thru_channels.cl","line":64}]],"replace_name":"true","type":"resource","data":[37,0,0,0],"children":[{"count":1,"name":"32-bit Integer Add","data":[33,0,0,0],"debug":[[{"filename":"/data/vkhriste/test-regression/multifit_ocl/device/fnnls_channels_pass_thru_channels.cl","line":64}]],"type":"resource"},{"count":2,"name":"5-bit Integer Add","data":[4,0,0,0],"debug":[[{"filename":"/data/vkhriste/test-regression/multifit_ocl/device/fnnls_channels_pass_thru_channels.cl","line":64}]],"type":"resource"}]},{"replace_name":"true","debug":[[{"filename":"/data/vkhriste/test-regression/multifit_ocl/device/fnnls_channels_pass_thru_channels.cl","line":71}]],"name":"/data/vkhriste/test-regression/multifit_ocl/device/fnnls_channels_pass_thru_channels.cl:71","children":[{"count":1,"name":"5-bit Integer Add","data":[2,0,0,0],"debug":[[{"filename":"/data/vkhriste/test-regression/multifit_ocl/device/fnnls_channels_pass_thru_channels.cl","line":71}]],"type":"resource"}],"data":[2,0,0,0],"type":"resource"},{"replace_name":"true","debug":[[{"filename":"/data/vkhriste/test-regression/multifit_ocl/device/fnnls_channels_pass_thru_channels.cl","line":67}]],"name":"/data/vkhriste/test-regression/multifit_ocl/device/fnnls_channels_pass_thru_channels.cl:67","children":[{"count":3,"name":"32-bit Integer Add","data":[55,0,0,0],"debug":[[{"filename":"/data/vkhriste/test-regression/multifit_ocl/device/fnnls_channels_pass_thru_channels.cl","line":67}]],"type":"resource"},{"count":2,"name":"5-bit Integer Add","data":[4,0,0,0],"debug":[[{"filename":"/data/vkhriste/test-regression/multifit_ocl/device/fnnls_channels_pass_thru_channels.cl","line":67}]],"type":"resource"}],"data":[59,0,0,0],"type":"resource"},{"replace_name":"true","debug":[[{"filename":"/data/vkhriste/test-regression/multifit_ocl/device/fnnls_channels_pass_thru_channels.cl","line":68}]],"name":"/data/vkhriste/test-regression/multifit_ocl/device/fnnls_channels_pass_thru_channels.cl:68","children":[{"count":2,"name":"32-bit Integer Add","data":[44,0,0,0],"debug":[[{"filename":"/data/vkhriste/test-regression/multifit_ocl/device/fnnls_channels_pass_thru_channels.cl","line":68}]],"type":"resource"},{"count":1,"name":"Load","data":[26,41,0,0],"debug":[[{"filename":"/data/vkhriste/test-regression/multifit_ocl/device/fnnls_channels_pass_thru_channels.cl","line":68}]],"type":"resource"}],"data":[70,41,0,0],"type":"resource"},{"replace_name":"true","debug":[[{"filename":"/data/vkhriste/test-regression/multifit_ocl/device/fnnls_channels_pass_thru_channels.cl","line":69}]],"name":"/data/vkhriste/test-regression/multifit_ocl/device/fnnls_channels_pass_thru_channels.cl:69","children":[{"count":1,"name":"5-bit Integer Add","data":[2,0,0,0],"debug":[[{"filename":"/data/vkhriste/test-regression/multifit_ocl/device/fnnls_channels_pass_thru_channels.cl","line":69}]],"type":"resource"}],"data":[2,0,0,0],"type":"resource"},{"replace_name":"true","debug":[[{"filename":"/data/vkhriste/test-regression/multifit_ocl/device/fnnls_channels_pass_thru_channels.cl","line":51}]],"name":"/data/vkhriste/test-regression/multifit_ocl/device/fnnls_channels_pass_thru_channels.cl:51","children":[{"count":1,"name":"And","data":[11,0,0,0],"debug":[[{"filename":"/data/vkhriste/test-regression/multifit_ocl/device/fnnls_channels_pass_thru_channels.cl","line":51}]],"type":"resource"},{"count":109,"name":"Or","data":[1199,0,0,0],"debug":[[{"filename":"/data/vkhriste/test-regression/multifit_ocl/device/fnnls_channels_pass_thru_channels.cl","line":51}]],"type":"resource"}],"data":[1210,0,0,0],"type":"resource"},{"replace_name":"true","debug":[[{"filename":"/data/vkhriste/test-regression/multifit_ocl/device/fnnls_channels_pass_thru_channels.cl","line":78}]],"name":"/data/vkhriste/test-regression/multifit_ocl/device/fnnls_channels_pass_thru_channels.cl:78","children":[{"count":1,"name":"And","data":[11,0,0,0],"debug":[[{"filename":"/data/vkhriste/test-regression/multifit_ocl/device/fnnls_channels_pass_thru_channels.cl","line":78}]],"type":"resource"}],"data":[11,0,0,0],"type":"resource"},{"replace_name":"true","debug":[[{"filename":"/data/vkhriste/test-regression/multifit_ocl/device/fnnls_channels_pass_thru_channels.cl","line":80}]],"name":"/data/vkhriste/test-regression/multifit_ocl/device/fnnls_channels_pass_thru_channels.cl:80","children":[{"count":1,"name":"Channel Write","data":[3,2,0,0],"debug":[[{"filename":"/data/vkhriste/test-regression/multifit_ocl/device/fnnls_channels_pass_thru_channels.cl","line":80}]],"type":"resource"}],"data":[3,2,0,0],"type":"resource"},{"replace_name":"true","debug":[[{"filename":"/data/vkhriste/test-regression/multifit_ocl/device/fnnls_channels_pass_thru_channels.cl","line":81}]],"name":"/data/vkhriste/test-regression/multifit_ocl/device/fnnls_channels_pass_thru_channels.cl:81","children":[{"count":1,"name":"Channel Write","data":[3,2,0,0],"debug":[[{"filename":"/data/vkhriste/test-regression/multifit_ocl/device/fnnls_channels_pass_thru_channels.cl","line":81}]],"type":"resource"},{"count":55,"name":"Load","data":[1430,2255,0,0],"debug":[[{"filename":"/data/vkhriste/test-regression/multifit_ocl/device/fnnls_channels_pass_thru_channels.cl","line":81}]],"type":"resource"}],"data":[1433,2257,0,0],"type":"resource"},{"replace_name":"true","debug":[[{"filename":"/data/vkhriste/test-regression/multifit_ocl/device/fnnls_channels_pass_thru_channels.cl","line":83}]],"name":"/data/vkhriste/test-regression/multifit_ocl/device/fnnls_channels_pass_thru_channels.cl:83","children":[{"count":1,"name":"Channel Write","data":[3,2,0,0],"debug":[[{"filename":"/data/vkhriste/test-regression/multifit_ocl/device/fnnls_channels_pass_thru_channels.cl","line":83}]],"type":"resource"}],"data":[3,2,0,0],"type":"resource"},{"replace_name":"true","debug":[[{"filename":"/data/vkhriste/test-regression/multifit_ocl/device/fnnls_channels_pass_thru_channels.cl","line":84}]],"name":"/data/vkhriste/test-regression/multifit_ocl/device/fnnls_channels_pass_thru_channels.cl:84","children":[{"count":1,"name":"Channel Write","data":[3,2,0,0],"debug":[[{"filename":"/data/vkhriste/test-regression/multifit_ocl/device/fnnls_channels_pass_thru_channels.cl","line":84}]],"type":"resource"},{"count":55,"name":"Load","data":[1430,2255,0,0],"debug":[[{"filename":"/data/vkhriste/test-regression/multifit_ocl/device/fnnls_channels_pass_thru_channels.cl","line":84}]],"type":"resource"}],"data":[1433,2257,0,0],"type":"resource"},{"replace_name":"true","debug":[[{"filename":"/data/vkhriste/test-regression/multifit_ocl/device/fnnls_channels_pass_thru_channels.cl","line":44}]],"name":"/data/vkhriste/test-regression/multifit_ocl/device/fnnls_channels_pass_thru_channels.cl:44","children":[{"count":1,"name":"32-bit Integer Add","data":[33,0,0,0],"debug":[[{"filename":"/data/vkhriste/test-regression/multifit_ocl/device/fnnls_channels_pass_thru_channels.cl","line":44}]],"type":"resource"},{"count":2,"name":"8-bit Integer Add","data":[6,0,0,0],"debug":[[{"filename":"/data/vkhriste/test-regression/multifit_ocl/device/fnnls_channels_pass_thru_channels.cl","line":44}]],"type":"resource"}],"data":[39,0,0,0],"type":"resource"},{"replace_name":"true","debug":[[{"filename":"/data/vkhriste/test-regression/multifit_ocl/device/fnnls_channels_pass_thru_channels.cl","line":45}]],"name":"/data/vkhriste/test-regression/multifit_ocl/device/fnnls_channels_pass_thru_channels.cl:45","children":[{"count":1,"name":"32-bit Integer Add","data":[33,0,0,0],"debug":[[{"filename":"/data/vkhriste/test-regression/multifit_ocl/device/fnnls_channels_pass_thru_channels.cl","line":45}]],"type":"resource"},{"count":1,"name":"8-bit Integer Add","data":[3,0,0,0],"debug":[[{"filename":"/data/vkhriste/test-regression/multifit_ocl/device/fnnls_channels_pass_thru_channels.cl","line":45}]],"type":"resource"},{"count":1,"name":"Load","data":[3038,4299,43,0],"debug":[[{"filename":"/data/vkhriste/test-regression/multifit_ocl/device/fnnls_channels_pass_thru_channels.cl","line":45}]],"type":"resource"},{"count":1,"name":"Store","data":[34,24,0,0],"debug":[[{"filename":"/data/vkhriste/test-regression/multifit_ocl/device/fnnls_channels_pass_thru_channels.cl","line":45}]],"type":"resource"}],"data":[3108,4323,43,0],"type":"resource"},{"replace_name":"true","debug":[[{"filename":"/data/vkhriste/test-regression/multifit_ocl/device/fnnls_channels_pass_thru_channels.cl","line":46}]],"name":"/data/vkhriste/test-regression/multifit_ocl/device/fnnls_channels_pass_thru_channels.cl:46","children":[{"count":1,"name":"32-bit Integer Add","data":[11,0,0,0],"debug":[[{"filename":"/data/vkhriste/test-regression/multifit_ocl/device/fnnls_channels_pass_thru_channels.cl","line":46}]],"type":"resource"}],"data":[11,0,0,0],"type":"resource"},{"replace_name":"true","debug":[[{"filename":"/data/vkhriste/test-regression/multifit_ocl/device/fnnls_channels_pass_thru_channels.cl","line":48}]],"name":"/data/vkhriste/test-regression/multifit_ocl/device/fnnls_channels_pass_thru_channels.cl:48","children":[{"count":1,"name":"32-bit Integer Add","data":[33,0,0,0],"debug":[[{"filename":"/data/vkhriste/test-regression/multifit_ocl/device/fnnls_channels_pass_thru_channels.cl","line":48}]],"type":"resource"},{"count":2,"name":"5-bit Integer Add","data":[4,0,0,0],"debug":[[{"filename":"/data/vkhriste/test-regression/multifit_ocl/device/fnnls_channels_pass_thru_channels.cl","line":48}]],"type":"resource"}],"data":[37,0,0,0],"type":"resource"},{"replace_name":"true","debug":[[{"filename":"/data/vkhriste/test-regression/multifit_ocl/device/fnnls_channels_pass_thru_channels.cl","line":49}]],"name":"/data/vkhriste/test-regression/multifit_ocl/device/fnnls_channels_pass_thru_channels.cl:49","children":[{"count":1,"name":"32-bit Integer Add","data":[33,0,0,0],"debug":[[{"filename":"/data/vkhriste/test-regression/multifit_ocl/device/fnnls_channels_pass_thru_channels.cl","line":49}]],"type":"resource"},{"count":1,"name":"5-bit Integer Add","data":[2,0,0,0],"debug":[[{"filename":"/data/vkhriste/test-regression/multifit_ocl/device/fnnls_channels_pass_thru_channels.cl","line":49}]],"type":"resource"},{"count":1,"name":"Load","data":[3038,4299,43,0],"debug":[[{"filename":"/data/vkhriste/test-regression/multifit_ocl/device/fnnls_channels_pass_thru_channels.cl","line":49}]],"type":"resource"}],"data":[3073,4299,43,0],"type":"resource"},{"name":"/data/vkhriste/test-regression/multifit_ocl/device/fnnls_channels_pass_thru_channels.cl:53","debug":[[{"filename":"/data/vkhriste/test-regression/multifit_ocl/device/fnnls_channels_pass_thru_channels.cl","line":53}]],"replace_name":"true","type":"resource","data":[62,0,0,0],"children":[{"count":1,"name":"5-bit Integer Add","data":[6,0,0,0],"debug":[[{"filename":"/data/vkhriste/test-regression/multifit_ocl/device/fnnls_channels_pass_thru_channels.cl","line":53}]],"type":"resource"},{"count":2,"name":"32-bit Integer Add","data":[22,0,0,0],"debug":[[{"filename":"/data/vkhriste/test-regression/multifit_ocl/device/fnnls_channels_pass_thru_channels.cl","line":53}]],"type":"resource"},{"count":1,"name":"33-bit Integer Add","data":[34,0,0,0],"debug":[[{"filename":"/data/vkhriste/test-regression/multifit_ocl/device/fnnls_channels_pass_thru_channels.cl","line":53}]],"type":"resource"}]},{"replace_name":"true","debug":[[{"filename":"/data/vkhriste/test-regression/multifit_ocl/device/fnnls_channels_pass_thru_channels.cl","line":55}]],"name":"/data/vkhriste/test-regression/multifit_ocl/device/fnnls_channels_pass_thru_channels.cl:55","children":[{"count":2,"name":"32-bit Integer Add","data":[66,0,0,0],"debug":[[{"filename":"/data/vkhriste/test-regression/multifit_ocl/device/fnnls_channels_pass_thru_channels.cl","line":55}]],"type":"resource"},{"count":2,"name":"33-bit Integer Add","data":[22.6667,0,0,0],"debug":[[{"filename":"/data/vkhriste/test-regression/multifit_ocl/device/fnnls_channels_pass_thru_channels.cl","line":55}]],"type":"resource"}],"data":[88.6667,0,0,0],"type":"resource"},{"replace_name":"true","debug":[[{"filename":"/data/vkhriste/test-regression/multifit_ocl/device/fnnls_channels_pass_thru_channels.cl","line":60}]],"name":"/data/vkhriste/test-regression/multifit_ocl/device/fnnls_channels_pass_thru_channels.cl:60","children":[{"count":2,"name":"32-bit Integer Add","data":[44,0,0,0],"debug":[[{"filename":"/data/vkhriste/test-regression/multifit_ocl/device/fnnls_channels_pass_thru_channels.cl","line":60}]],"type":"resource"},{"count":1,"name":"Store","data":[34,24,0,0],"debug":[[{"filename":"/data/vkhriste/test-regression/multifit_ocl/device/fnnls_channels_pass_thru_channels.cl","line":60}]],"type":"resource"}],"data":[78,24,0,0],"type":"resource"},{"replace_name":"true","debug":[[{"filename":"/data/vkhriste/test-regression/multifit_ocl/device/fnnls_channels_pass_thru_channels.cl","line":61}]],"name":"/data/vkhriste/test-regression/multifit_ocl/device/fnnls_channels_pass_thru_channels.cl:61","children":[{"count":1,"name":"33-bit Integer Add","data":[11.3333,0,0,0],"debug":[[{"filename":"/data/vkhriste/test-regression/multifit_ocl/device/fnnls_channels_pass_thru_channels.cl","line":61}]],"type":"resource"}],"data":[11.3333,0,0,0],"type":"resource"},{"replace_name":"true","debug":[[{"filename":"/data/vkhriste/test-regression/multifit_ocl/device/fnnls_channels_pass_thru_channels.cl","line":58}]],"name":"/data/vkhriste/test-regression/multifit_ocl/device/fnnls_channels_pass_thru_channels.cl:58","children":[{"count":3,"name":"32-bit Integer Add","data":[55,0,0,0],"debug":[[{"filename":"/data/vkhriste/test-regression/multifit_ocl/device/fnnls_channels_pass_thru_channels.cl","line":58}]],"type":"resource"},{"count":2,"name":"5-bit Integer Add","data":[4,0,0,0],"debug":[[{"filename":"/data/vkhriste/test-regression/multifit_ocl/device/fnnls_channels_pass_thru_channels.cl","line":58}]],"type":"resource"}],"data":[59,0,0,0],"type":"resource"},{"replace_name":"true","debug":[[{"filename":"/data/vkhriste/test-regression/multifit_ocl/device/fnnls_channels_pass_thru_channels.cl","line":59}]],"name":"/data/vkhriste/test-regression/multifit_ocl/device/fnnls_channels_pass_thru_channels.cl:59","children":[{"count":3,"name":"32-bit Integer Add","data":[77,0,0,0],"debug":[[{"filename":"/data/vkhriste/test-regression/multifit_ocl/device/fnnls_channels_pass_thru_channels.cl","line":59}]],"type":"resource"},{"count":1,"name":"5-bit Integer Add","data":[2,0,0,0],"debug":[[{"filename":"/data/vkhriste/test-regression/multifit_ocl/device/fnnls_channels_pass_thru_channels.cl","line":59}]],"type":"resource"},{"count":2,"name":"Load","data":[52,82,0,0],"debug":[[{"filename":"/data/vkhriste/test-regression/multifit_ocl/device/fnnls_channels_pass_thru_channels.cl","line":59}]],"type":"resource"}],"data":[131,82,0,0],"type":"resource"}],"data":[26131,29280,162,2],"details":[{"text":"Number of compute units: 1","type":"text"},{"text":"Max global work dimension: 0","type":"text"},{"text":"The following loop is nested at depth greater than 3. Reducing the depth of this nested loop will save area:","type":"text","details":[{"text":"%L with depth 4","type":"text","links":[{"filename":"/data/vkhriste/test-regression/multifit_ocl/device/fnnls_channels_pass_thru_channels.cl","line":58}]}]}],"compute_units":1},{"name":"fnnls_worker_0_0_0","total_kernel_resources":[1065,1333,0,0],"debug":[[{"filename":"/data/vkhriste/test-regression/multifit_ocl/device/fnnls_channels_pass_thru_channels.cl","line":102}]],"type":"function","total_percent":[0.220105,0.143822,0.0900068,0,0],"children":[{"detail":[{"text":"Feedback + Cluster logic","type":"text"}],"name":"Data control overhead","type":"resource","data":[571,933,0,0]},{"name":"Private Variable: \n - 'i' (fnnls_channels_pass_thru_channels.cl:104)","type":"resource","data":[7,36,0,0],"details":[{"text":"Type: Register","type":"text"},{"text":"1 register of width 32 and depth 1","type":"text"}]},{"name":"Private Variable: \n - 'result' (fnnls_channels_pass_thru_channels.cl:102)","type":"resource","data":[70,360,0,0],"details":[{"text":"Type: Register","type":"text"},{"text":"10 registers of width 32 and depth 1","type":"text"}]},{"name":"/data/vkhriste/test-regression/multifit_ocl/device/fnnls_channels_pass_thru_channels.cl:98","debug":[[{"filename":"/data/vkhriste/test-regression/multifit_ocl/device/fnnls_channels_pass_thru_channels.cl","line":98}]],"replace_name":"true","type":"resource","data":[1,0,0,0],"children":[{"count":1,"name":"Channel Read","data":[1,0,0,0],"debug":[[{"filename":"/data/vkhriste/test-regression/multifit_ocl/device/fnnls_channels_pass_thru_channels.cl","line":98}]],"type":"resource"}]},{"replace_name":"true","debug":[[{"filename":"/data/vkhriste/test-regression/multifit_ocl/device/fnnls_channels_pass_thru_channels.cl","line":99}]],"name":"/data/vkhriste/test-regression/multifit_ocl/device/fnnls_channels_pass_thru_channels.cl:99","children":[{"count":1,"name":"Channel Read","data":[1,0,0,0],"debug":[[{"filename":"/data/vkhriste/test-regression/multifit_ocl/device/fnnls_channels_pass_thru_channels.cl","line":99}]],"type":"resource"}],"data":[1,0,0,0],"type":"resource"},{"name":"No Source Line","debug":[[{"filename":"","line":0}]],"type":"resource","data":[370,0,0,0],"children":[{"count":10,"name":"Integer Compare","data":[110,0,0,0],"debug":[[{"filename":"","line":0}]],"type":"resource"},{"count":10,"name":"Select","data":[260,0,0,0],"debug":[[{"filename":"","line":0}]],"type":"resource"}]},{"replace_name":"true","debug":[[{"filename":"/data/vkhriste/test-regression/multifit_ocl/device/fnnls_channels_pass_thru_channels.cl","line":104}]],"name":"/data/vkhriste/test-regression/multifit_ocl/device/fnnls_channels_pass_thru_channels.cl:104","children":[{"count":1,"name":"32-bit Integer Add","data":[33,0,0,0],"debug":[[{"filename":"/data/vkhriste/test-regression/multifit_ocl/device/fnnls_channels_pass_thru_channels.cl","line":104}]],"type":"resource"},{"count":2,"name":"5-bit Integer Add","data":[4,0,0,0],"debug":[[{"filename":"/data/vkhriste/test-regression/multifit_ocl/device/fnnls_channels_pass_thru_channels.cl","line":104}]],"type":"resource"}],"data":[37,0,0,0],"type":"resource"},{"replace_name":"true","debug":[[{"filename":"/data/vkhriste/test-regression/multifit_ocl/device/fnnls_channels_pass_thru_channels.cl","line":105}]],"name":"/data/vkhriste/test-regression/multifit_ocl/device/fnnls_channels_pass_thru_channels.cl:105","children":[{"count":1,"name":"5-bit Integer Add","data":[2,0,0,0],"debug":[[{"filename":"/data/vkhriste/test-regression/multifit_ocl/device/fnnls_channels_pass_thru_channels.cl","line":105}]],"type":"resource"}],"data":[2,0,0,0],"type":"resource"},{"name":"/data/vkhriste/test-regression/multifit_ocl/device/fnnls_channels_pass_thru_channels.cl:108","debug":[[{"filename":"/data/vkhriste/test-regression/multifit_ocl/device/fnnls_channels_pass_thru_channels.cl","line":108}]],"replace_name":"true","type":"resource","data":[3,2,0,0],"children":[{"count":1,"name":"Channel Write","data":[3,2,0,0],"debug":[[{"filename":"/data/vkhriste/test-regression/multifit_ocl/device/fnnls_channels_pass_thru_channels.cl","line":108}]],"type":"resource"}]},{"replace_name":"true","debug":[[{"filename":"/data/vkhriste/test-regression/multifit_ocl/device/fnnls_channels_pass_thru_channels.cl","line":109}]],"name":"/data/vkhriste/test-regression/multifit_ocl/device/fnnls_channels_pass_thru_channels.cl:109","children":[{"count":1,"name":"Channel Write","data":[3,2,0,0],"debug":[[{"filename":"/data/vkhriste/test-regression/multifit_ocl/device/fnnls_channels_pass_thru_channels.cl","line":109}]],"type":"resource"}],"data":[3,2,0,0],"type":"resource"}],"data":[1065,1333,0,0],"details":[{"text":"Number of compute units: 1","type":"text"},{"text":"Max global work dimension: 0","type":"text"}],"compute_units":1},{"name":"fnnls_worker_1_0_0","total_kernel_resources":[1065,1333,0,0],"debug":[[{"filename":"/data/vkhriste/test-regression/multifit_ocl/device/fnnls_channels_pass_thru_channels.cl","line":102}]],"type":"function","total_percent":[0.220105,0.143822,0.0900068,0,0],"children":[{"detail":[{"text":"Feedback + Cluster logic","type":"text"}],"name":"Data control overhead","type":"resource","data":[571,933,0,0]},{"name":"Private Variable: \n - 'i' (fnnls_channels_pass_thru_channels.cl:104)","type":"resource","data":[7,36,0,0],"details":[{"text":"Type: Register","type":"text"},{"text":"1 register of width 32 and depth 1","type":"text"}]},{"name":"Private Variable: \n - 'result' (fnnls_channels_pass_thru_channels.cl:102)","type":"resource","data":[70,360,0,0],"details":[{"text":"Type: Register","type":"text"},{"text":"10 registers of width 32 and depth 1","type":"text"}]},{"name":"/data/vkhriste/test-regression/multifit_ocl/device/fnnls_channels_pass_thru_channels.cl:98","debug":[[{"filename":"/data/vkhriste/test-regression/multifit_ocl/device/fnnls_channels_pass_thru_channels.cl","line":98}]],"replace_name":"true","type":"resource","data":[1,0,0,0],"children":[{"count":1,"name":"Channel Read","data":[1,0,0,0],"debug":[[{"filename":"/data/vkhriste/test-regression/multifit_ocl/device/fnnls_channels_pass_thru_channels.cl","line":98}]],"type":"resource"}]},{"replace_name":"true","debug":[[{"filename":"/data/vkhriste/test-regression/multifit_ocl/device/fnnls_channels_pass_thru_channels.cl","line":99}]],"name":"/data/vkhriste/test-regression/multifit_ocl/device/fnnls_channels_pass_thru_channels.cl:99","children":[{"count":1,"name":"Channel Read","data":[1,0,0,0],"debug":[[{"filename":"/data/vkhriste/test-regression/multifit_ocl/device/fnnls_channels_pass_thru_channels.cl","line":99}]],"type":"resource"}],"data":[1,0,0,0],"type":"resource"},{"name":"No Source Line","debug":[[{"filename":"","line":0}]],"type":"resource","data":[370,0,0,0],"children":[{"count":10,"name":"Integer Compare","data":[110,0,0,0],"debug":[[{"filename":"","line":0}]],"type":"resource"},{"count":10,"name":"Select","data":[260,0,0,0],"debug":[[{"filename":"","line":0}]],"type":"resource"}]},{"replace_name":"true","debug":[[{"filename":"/data/vkhriste/test-regression/multifit_ocl/device/fnnls_channels_pass_thru_channels.cl","line":104}]],"name":"/data/vkhriste/test-regression/multifit_ocl/device/fnnls_channels_pass_thru_channels.cl:104","children":[{"count":1,"name":"32-bit Integer Add","data":[33,0,0,0],"debug":[[{"filename":"/data/vkhriste/test-regression/multifit_ocl/device/fnnls_channels_pass_thru_channels.cl","line":104}]],"type":"resource"},{"count":2,"name":"5-bit Integer Add","data":[4,0,0,0],"debug":[[{"filename":"/data/vkhriste/test-regression/multifit_ocl/device/fnnls_channels_pass_thru_channels.cl","line":104}]],"type":"resource"}],"data":[37,0,0,0],"type":"resource"},{"replace_name":"true","debug":[[{"filename":"/data/vkhriste/test-regression/multifit_ocl/device/fnnls_channels_pass_thru_channels.cl","line":105}]],"name":"/data/vkhriste/test-regression/multifit_ocl/device/fnnls_channels_pass_thru_channels.cl:105","children":[{"count":1,"name":"5-bit Integer Add","data":[2,0,0,0],"debug":[[{"filename":"/data/vkhriste/test-regression/multifit_ocl/device/fnnls_channels_pass_thru_channels.cl","line":105}]],"type":"resource"}],"data":[2,0,0,0],"type":"resource"},{"name":"/data/vkhriste/test-regression/multifit_ocl/device/fnnls_channels_pass_thru_channels.cl:108","debug":[[{"filename":"/data/vkhriste/test-regression/multifit_ocl/device/fnnls_channels_pass_thru_channels.cl","line":108}]],"replace_name":"true","type":"resource","data":[3,2,0,0],"children":[{"count":1,"name":"Channel Write","data":[3,2,0,0],"debug":[[{"filename":"/data/vkhriste/test-regression/multifit_ocl/device/fnnls_channels_pass_thru_channels.cl","line":108}]],"type":"resource"}]},{"replace_name":"true","debug":[[{"filename":"/data/vkhriste/test-regression/multifit_ocl/device/fnnls_channels_pass_thru_channels.cl","line":109}]],"name":"/data/vkhriste/test-regression/multifit_ocl/device/fnnls_channels_pass_thru_channels.cl:109","children":[{"count":1,"name":"Channel Write","data":[3,2,0,0],"debug":[[{"filename":"/data/vkhriste/test-regression/multifit_ocl/device/fnnls_channels_pass_thru_channels.cl","line":109}]],"type":"resource"}],"data":[3,2,0,0],"type":"resource"}],"data":[1065,1333,0,0],"details":[{"text":"Number of compute units: 1","type":"text"},{"text":"Max global work dimension: 0","type":"text"}],"compute_units":1}],"data":[38384,63495,262,2],"total_percent":[38.9514,20.565,19.6688,27.3545,0.131752],"total":[152284,291295,639,2],"debug_enabled":"true","columns":["","ALUTs","FFs","RAMs","DSPs","Details"],"type":"module"}